onchaindata/__init__.py
onchaindata/data_extraction/__init__.py
onchaindata/data_extraction/base.py
onchaindata/data_extraction/etherscan.py
onchaindata/data_extraction/rate_limiter.py
onchaindata/utils/chain.py
onchaindata-0.0.8.dist-info/METADATA
onchaindata-0.0.8.dist-info/WHEEL
onchaindata-0.0.8.dist-info/top_level.txt
onchaindata-0.0.8.dist-info/RECORD
