Metadata-Version: 2.4
Name: onchaindata
Version: 0.0.8
Summary: Toolkit for getting onchain data
Requires-Python: >=3.11
Requires-Dist: dlt[duckdb]>=1.14.1
Requires-Dist: eth-hash[pycryptodome]>=0.7.1
Requires-Dist: pytest>=8.4.1
Requires-Dist: python-dotenv>=1.1.1
Requires-Dist: requests>=2.32.4
